.DS_Store
mangascandl/__init__.py
mangascandl/mangascandl.py
mangascandl/extractor/Mangadex.py
mangascandl/extractor/Mangareader.py
mangascandl/extractor/__init__.py
mangascandl/extractor/common.py
mangascandl/extractor/model.py
mangascandl-1.0.3.dist-info/METADATA
mangascandl-1.0.3.dist-info/RECORD
mangascandl-1.0.3.dist-info/WHEEL
mangascandl-1.0.3.dist-info/entry_points.txt
mangascandl-1.0.3.dist-info/top_level.txt
