Metadata-Version: 2.1
Name: mangascandl
Version: 1.0.3
Summary: Tool for downloading mangascan from websites
Home-page: https://github.com/SuarthaGautama/mangascandl
Author: Suartha Gautama
Author-email: suartha.gautama@gmail.com
License: UNKNOWN
Platform: UNKNOWN
Requires-Dist: tqdm
Requires-Dist: beautifulsoup4
